README.md
setup.py
pyrainzplay/NumpyApplication.py
pyrainzplay/__init__.py
pyrainzplay.egg-info/PKG-INFO
pyrainzplay.egg-info/SOURCES.txt
pyrainzplay.egg-info/dependency_links.txt
pyrainzplay.egg-info/requires.txt
pyrainzplay.egg-info/top_level.txt
pyrainzplay/funclib/Addition.py
pyrainzplay/funclib/__init__.py
pyrainzplay/scripts/Calculator.py
pyrainzplay/scripts/__init__.py