Metadata-Version: 1.1
Name: pyrainzplay
Version: 0.0.6
Summary: Playground app for py first timers!
Home-page: https://github.com/cbludev/pyrainzplay
Author: Rainz
Author-email: cbludev@gmail.com
License: Personal
Download-URL: https://github.com/cbludev/pyrainzplay/archive/0.0.6.zip
Keywords: numpy
Platform: UNKNOWN
